pyCIF-0.0.2.data/scripts/mirror_NILU.sh
pyCIF-0.0.2.data/scripts/pull_NILU.sh
pyCIF-0.0.2.data/scripts/push_NILU.sh
pyCIF-0.0.2.data/scripts/pycif.sh
pycif/__init__.py
pycif/__main__.py
pycif/plugins/__init__.py
pycif/plugins/chemistries/__init__.py
pycif/plugins/chemistries/register.py
pycif/plugins/chemistries/chimere/__init__.py
pycif/plugins/chemistries/chimere/make_chemistry.py
pycif/plugins/chemistries/chimere/read_chemistry.py
pycif/plugins/chemistries/chimere/utils.py
pycif/plugins/controlvects/__init__.py
pycif/plugins/controlvects/register.py
pycif/plugins/controlvects/standard/__init__.py
pycif/plugins/controlvects/standard/build_hcorr.py
pycif/plugins/controlvects/standard/build_tcorr.py
pycif/plugins/controlvects/standard/control2native.py
pycif/plugins/controlvects/standard/dump.py
pycif/plugins/controlvects/standard/init_bprod.py
pycif/plugins/controlvects/standard/init_xb.py
pycif/plugins/controlvects/standard/native2control.py
pycif/plugins/controlvects/standard/sqrtbprod.py
pycif/plugins/controlvects/standard/utils/__init__.py
pycif/plugins/controlvects/standard/utils/dates.py
pycif/plugins/controlvects/standard/utils/dimensions.py
pycif/plugins/controlvects/standard/utils/reindex.py
pycif/plugins/controlvects/standard/utils/scalemaps.py
pycif/plugins/domains/__init__.py
pycif/plugins/domains/register.py
pycif/plugins/domains/chimere/__init__.py
pycif/plugins/domains/chimere/create_domain.py
pycif/plugins/domains/chimere/read_domain.py
pycif/plugins/domains/dummy/__init__.py
pycif/plugins/domains/dummy/create_domain.py
pycif/plugins/domains/dummy/read_domain.py
pycif/plugins/domains/lmdz/__init__.py
pycif/plugins/domains/lmdz/create_domain.py
pycif/plugins/domains/lmdz/read_domain.py
pycif/plugins/fields/__init__.py
pycif/plugins/fields/register.py
pycif/plugins/fields/chimere_icbc/__init__.py
pycif/plugins/fields/chimere_icbc/read.py
pycif/plugins/fields/chimere_icbc/write.py
pycif/plugins/fields/lmdz_ic/__init__.py
pyCIF-0.0.2.dist-info/LICENSE
pyCIF-0.0.2.dist-info/METADATA
pyCIF-0.0.2.dist-info/WHEEL
pyCIF-0.0.2.dist-info/top_level.txt
pyCIF-0.0.2.dist-info/RECORD
