Metadata-Version: 2.1
Name: pyCIF
Version: 0.0.2
Summary: A Python-based interface to the Community Inversion Framework
Home-page: UNKNOWN
License: UNKNOWN
Platform: UNKNOWN
Requires-Python: >=2.7,<3
Requires-Dist: numpy
Requires-Dist: scipy (<=1.2)
Requires-Dist: matplotlib (<3)
Requires-Dist: pandas
Requires-Dist: netCDF4
Requires-Dist: pytz
Requires-Dist: python-dateutil
Requires-Dist: xarray (<=0.11)
Requires-Dist: pyyaml
Requires-Dist: pyproj
Requires-Dist: psutil
Requires-Dist: Pillow (<7)
Provides-Extra: dev
Requires-Dist: Sphinx ; extra == 'dev'
Requires-Dist: sphinx-rtd-theme ; extra == 'dev'
Requires-Dist: sphinxcontrib-napoleon ; extra == 'dev'
